anysecret/__init__.py
anysecret/config.py
anysecret/config_loader.py
anysecret/config_manager.py
anysecret/parameter_manager.py
anysecret/secret_manager.py
anysecret/cli/__init__.py
anysecret/cli/cli.py
anysecret/cli/main.py
anysecret/cli/commands/__init__.py
anysecret/cli/commands/bulk_commands.py
anysecret/cli/commands/cicd_commands.py
anysecret/cli/commands/config_commands.py
anysecret/cli/commands/debug_commands.py
anysecret/cli/commands/env_commands.py
anysecret/cli/commands/multicloud_commands.py
anysecret/cli/commands/providers_commands.py
anysecret/cli/commands/read_commands.py
anysecret/cli/commands/security_commands.py
anysecret/cli/commands/sync_commands.py
anysecret/cli/commands/write_commands.py
anysecret/cli/core/__init__.py
anysecret/cli/core/config.py
anysecret/cli/core/context.py
anysecret/cli/core/decorators.py
anysecret/cli/core/utils.py
anysecret/providers/__init__.py
anysecret/providers/aws.py
anysecret/providers/aws_parameter_manager.py
anysecret/providers/aws_s3_parameter_manager.py
anysecret/providers/azure.py
anysecret/providers/azure_blob_parameter_manager.py
anysecret/providers/azure_parameter_manager.py
anysecret/providers/cloud_storage_base.py
anysecret/providers/file.py
anysecret/providers/file_parameter_manager.py
anysecret/providers/gcp.py
anysecret/providers/gcp_parameter_manager.py
anysecret/providers/gcs_parameter_manager.py
anysecret/providers/k8s.py
anysecret/providers/kubernetes_parameter_manager.py
anysecret/providers/vault.py
anysecret_io-1.2.0.dist-info/licenses/LICENSE
anysecret_io-1.2.0.dist-info/METADATA
anysecret_io-1.2.0.dist-info/WHEEL
anysecret_io-1.2.0.dist-info/entry_points.txt
anysecret_io-1.2.0.dist-info/top_level.txt
anysecret_io-1.2.0.dist-info/RECORD
