Metadata-Version: 2.4
Name: anysecret-io
Version: 1.2.0
Summary: Universal secret manager for applications and CI/CD tools with CLI interface and multi-cloud support
Author-email: "AnySecret.io Team" <hello@anysecret.io>
License: MIT
Project-URL: Homepage, https://anysecret.io/
Project-URL: Documentation, https://github.com/anysecret-io/anysecret-lib/docs/quickstart.md
Project-URL: Repository, https://github.com/anysecret-io/anysecret-lib
Project-URL: Bug Tracker, https://github.com/anysecret-io/anysecret-lib/issues
Keywords: secrets,secret-management,cloud,aws,gcp,azure,vault,fastapi,async
Classifier: Development Status :: 4 - Beta
Classifier: Intended Audience :: Developers
Classifier: Topic :: Software Development :: Libraries :: Python Modules
Classifier: Topic :: System :: Systems Administration
Classifier: Topic :: Security
Classifier: License :: OSI Approved :: MIT License
Classifier: Operating System :: OS Independent
Classifier: Programming Language :: Python :: 3
Classifier: Programming Language :: Python :: 3.10
Classifier: Programming Language :: Python :: 3.11
Classifier: Programming Language :: Python :: 3.12
Classifier: Programming Language :: Python :: 3 :: Only
Classifier: Framework :: AsyncIO
Classifier: Framework :: FastAPI
Requires-Python: >=3.10
License-File: LICENSE
Requires-Dist: cryptography>=3.4.0
Requires-Dist: pydantic>=2.0.0
Requires-Dist: typer>=0.9.0
Requires-Dist: rich>=13.0.0
Requires-Dist: aiofiles>=22.0.0
Requires-Dist: PyYAML>=6.0
Provides-Extra: gcp
Requires-Dist: google-cloud-secret-manager>=2.16.0; extra == "gcp"
Requires-Dist: google-auth>=2.16.0; extra == "gcp"
Provides-Extra: aws
Requires-Dist: boto3>=1.26.0; extra == "aws"
Requires-Dist: botocore>=1.29.0; extra == "aws"
Provides-Extra: azure
Requires-Dist: azure-keyvault-secrets>=4.7.0; extra == "azure"
Requires-Dist: azure-identity>=1.12.0; extra == "azure"
Requires-Dist: azure-appconfiguration>=1.4.0; extra == "azure"
Provides-Extra: k8s
Requires-Dist: kubernetes>=25.0.0; extra == "k8s"
Provides-Extra: vault
Requires-Dist: hvac>=1.0.0; extra == "vault"
Provides-Extra: all
Requires-Dist: google-cloud-secret-manager>=2.16.0; extra == "all"
Requires-Dist: google-auth>=2.16.0; extra == "all"
Requires-Dist: boto3>=1.26.0; extra == "all"
Requires-Dist: botocore>=1.29.0; extra == "all"
Requires-Dist: azure-keyvault-secrets>=4.7.0; extra == "all"
Requires-Dist: azure-identity>=1.12.0; extra == "all"
Requires-Dist: azure-appconfiguration>=1.4.0; extra == "all"
Requires-Dist: kubernetes>=25.0.0; extra == "all"
Requires-Dist: hvac>=1.0.0; extra == "all"
Provides-Extra: dev
Requires-Dist: pytest>=7.0.0; extra == "dev"
Requires-Dist: pytest-asyncio>=0.21.0; extra == "dev"
Requires-Dist: pytest-cov>=4.0.0; extra == "dev"
Requires-Dist: black>=22.0.0; extra == "dev"
Requires-Dist: isort>=5.10.0; extra == "dev"
Requires-Dist: flake8>=5.0.0; extra == "dev"
Requires-Dist: mypy>=1.0.0; extra == "dev"
Requires-Dist: pre-commit>=2.20.0; extra == "dev"
Requires-Dist: twine>=4.0.0; extra == "dev"
Requires-Dist: build>=0.8.0; extra == "dev"
Dynamic: license-file
